antimatter/__init__.py
antimatter/capsule.py
antimatter/cell_utils.py
antimatter/extra_helper.py
antimatter/session.py
antimatter/auth/__init__.py
antimatter/auth/config/__init__.py
antimatter/auth/config/auth_config.py
antimatter/auth/config/global_identity.py
antimatter/auth/config/profiles.py
antimatter/auth/config/tokens.py
antimatter/authn/__init__.py
antimatter/authn/apikey.py
antimatter/authn/base.py
antimatter/authn/google_oauth.py
antimatter/authn/oauth_domain.py
antimatter/authn/oauth_global.py
antimatter/authn/static_oauth.py
antimatter/authn/unauth.py
antimatter/authz/__init__.py
antimatter/authz/base.py
antimatter/authz/token.py
antimatter/builders/__init__.py
antimatter/builders/capability.py
antimatter/builders/data_policy.py
antimatter/builders/fact_policy.py
antimatter/builders/identity_provider.py
antimatter/builders/read_context.py
antimatter/builders/root_encryption_key.py
antimatter/builders/settings_put.py
antimatter/builders/write_context.py
antimatter/builders/write_context_rule.py
antimatter/cap_prep/__init__.py
antimatter/cap_prep/applicator.py
antimatter/cap_prep/prep.py
antimatter/cap_prep/tests/__init__.py
antimatter/cap_prep/tests/test_applicator.py
antimatter/cap_prep/tests/test_prep.py
antimatter/constants/__init__.py
antimatter/constants/capability.py
antimatter/constants/domain_policy.py
antimatter/constants/fact_policy.py
antimatter/constants/hooks.py
antimatter/constants/identity_provider.py
antimatter/constants/read_context_rule.py
antimatter/constants/write_context.py
antimatter/converters/__init__.py
antimatter/converters/capability.py
antimatter/converters/tags.py
antimatter/datatype/__init__.py
antimatter/datatype/datatypes.py
antimatter/datatype/infer.py
antimatter/datatype/tests/__init__.py
antimatter/datatype/tests/test_factory.py
antimatter/dependencies/__init__.py
antimatter/dependencies/package_hint.py
antimatter/dependencies/data/pyproject.toml
antimatter/dependencies/tests/__init__.py
antimatter-2.0.4.dist-info/METADATA
antimatter-2.0.4.dist-info/WHEEL
antimatter-2.0.4.dist-info/top_level.txt
antimatter-2.0.4.dist-info/RECORD
