Metadata-Version: 2.1
Name: antimatter
Version: 2.0.4
Summary: Library for interacting with capsules in various formats
Author-email: Antimatter Team <support@antimatter.io>
Project-URL: Docs, https://antimatter-python-client.readthedocs-hosted.com/
Requires-Python: >=3.8
Requires-Dist: antimatter-engine==2.0.4
Requires-Dist: annotated_types>=0.6
Requires-Dist: packaging>=21.1
Requires-Dist: pydantic>=2.0
Requires-Dist: python-dateutil>=2.7.0
Requires-Dist: pyyaml
Requires-Dist: cbor2~=5.5
Requires-Dist: urllib3>=2.0.2
Requires-Dist: google-auth>=2.29.0
Requires-Dist: requests>=2.31.0
Requires-Dist: safer>=4.0
Requires-Dist: tomli>=2.0.1
Requires-Dist: antimatter_api==2.0.10
Provides-Extra: dev
Requires-Dist: pytest>=7.0; extra == "dev"
Provides-Extra: langchain
Requires-Dist: langchain>=0.0.341; extra == "langchain"
Requires-Dist: faiss-cpu>=1.7.3; extra == "langchain"
Requires-Dist: numpy>=1.26; extra == "langchain"
Requires-Dist: langchain_community>=0.2.0; extra == "langchain"
Provides-Extra: langchain-huggingface
Requires-Dist: langchain>=0.0.341; extra == "langchain-huggingface"
Requires-Dist: faiss-cpu>=1.7.3; extra == "langchain-huggingface"
Requires-Dist: transformers>=4.23; extra == "langchain-huggingface"
Requires-Dist: torch>=2.0; extra == "langchain-huggingface"
Requires-Dist: numpy>=1.26; extra == "langchain-huggingface"
Provides-Extra: numpy
Requires-Dist: numpy>=1.23.3; extra == "numpy"
Provides-Extra: pandas
Requires-Dist: pandas[performance]>=1.5; extra == "pandas"
Provides-Extra: pyarrow
Requires-Dist: pandas[performance]>=2.0; extra == "pyarrow"
Requires-Dist: pyarrow>=2.0; extra == "pyarrow"
Provides-Extra: pytorch
Requires-Dist: torch>=2.0; extra == "pytorch"
Provides-Extra: all
Requires-Dist: langchain>=0.0.341; extra == "all"
Requires-Dist: faiss-cpu>=1.7.3; extra == "all"
Requires-Dist: transformers>=4.23; extra == "all"
Requires-Dist: torch>=2.0; extra == "all"
Requires-Dist: numpy>=1.23.3; extra == "all"
Requires-Dist: pandas[performance]>=2.0; extra == "all"
Requires-Dist: pyarrow>=2.0; extra == "all"
Requires-Dist: langchain_community>=0.2.0; extra == "all"
